stela/__init__.py
stela/asyncio.py
stela/cmd/.env
stela/cmd/.gitignore
stela/cmd/.stela
stela/cmd/__init__.py
stela/cmd/foo/.env
stela/cmd/stela_cmd.py
stela/cmd/stela_init.py
stela/config.py
stela/decorators.py
stela/exceptions.py
stela/helpers/__init__.py
stela/helpers/pydantic.py
stela/helpers/stub.py
stela/main.py
stela/parsers/__init__.py
stela/parsers/dotenv.py
stela/parsers/reader.py
stela/utils.py
stela-8.1.1.dist-info/LICENSE
stela-8.1.1.dist-info/METADATA
stela-8.1.1.dist-info/WHEEL
stela-8.1.1.dist-info/entry_points.txt
stela-8.1.1.dist-info/RECORD
