Metadata-Version: 2.3
Name: stela
Version: 8.1.1
Summary: Organize your project settings and secrets with ease
License: MIT
Keywords: settings,configuration,parser,dotenv,environment
Author: Chris Maillefaud
Author-email: chrismaille@users.noreply.github.com
Requires-Python: >=3.11,<4.0
Classifier: Development Status :: 4 - Beta
Classifier: Environment :: Plugins
Classifier: Intended Audience :: Developers
Classifier: License :: OSI Approved :: MIT License
Classifier: Programming Language :: Python :: 3
Classifier: Programming Language :: Python :: 3.11
Classifier: Programming Language :: Python :: 3.12
Classifier: Programming Language :: Python :: 3.13
Classifier: Topic :: Software Development :: Libraries
Requires-Dist: click
Requires-Dist: loguru
Requires-Dist: python-dotenv
Requires-Dist: toml
Requires-Dist: tomlkit
Project-URL: Repository, https://github.com/megalus/stela
